nju_deepseek/__init__.py
nju_deepseek/__main__.py
nju_deepseek/chat.py
nju_deepseek/cli.py
nju_deepseek/utils/__init__.py
nju_deepseek/utils/auth.py
nju_deepseek/utils/common.onnx
nju_deepseek/utils/ddddocr.py
nju_deepseek-0.3.1.dist-info/licenses/LICENSE
nju_deepseek-0.3.1.dist-info/WHEEL
nju_deepseek-0.3.1.dist-info/entry_points.txt
nju_deepseek-0.3.1.dist-info/METADATA
nju_deepseek-0.3.1.dist-info/RECORD
