Metadata-Version: 2.4
Name: nju-deepseek
Version: 0.3.1
Summary: A Python package for accessing agents listed on https://chat.nju.edu.cn/deepseek via command-line interface.
Author: Nemowang
Author-email: Nemowang <211108100@smail.nju.edu.cn>
License-Expression: MIT
License-File: LICENSE
Requires-Dist: python-socketio[client]>=5.13.0
Requires-Dist: requests>=2.32.3
Requires-Dist: tenacity>=9.1.2
Requires-Dist: websocket-client>=1.8.0
Requires-Dist: lxml>=5.4.0 ; extra == 'auth'
Requires-Dist: onnxruntime>=1.22.0 ; extra == 'auth'
Requires-Dist: pillow>=11.2.1 ; extra == 'auth'
Requires-Dist: pycryptodomex>=3.23.0 ; extra == 'auth'
Requires-Dist: platformdirs>=4.3.8 ; extra == 'cli'
Requires-Dist: prompt-toolkit>=3.0.51 ; extra == 'cli'
Requires-Python: >=3.13
Provides-Extra: auth
Provides-Extra: cli
